file_converter/__init__.py
file_converter/csv2json.py
file_converter/file_converter.py
file_converter/json2csv.py
file_converter/utils.py
file_converter_fgsm-0.1.3.dist-info/entry_points.txt
file_converter_fgsm-0.1.3.dist-info/LICENSE
file_converter_fgsm-0.1.3.dist-info/WHEEL
file_converter_fgsm-0.1.3.dist-info/METADATA
file_converter_fgsm-0.1.3.dist-info/RECORD
